{"to the": 181, "begsent live": 179, "live your": 179, "your life": 179, "life to": 179, "the fullest": 179, "fullest no": 179, "no regrets": 179, "regrets endsent": 179, "da shocka": 19, "shocka endsent": 19, "begsent i": 15, "begsent ucsc": 12, "ucsc \u201822": 12, "\u201822 /silkk": 12, "/silkk da": 12, "begsent ags": 12, "ags \u26a1\ufe0f": 12, "\u26a1\ufe0f endsent": 12, "i am": 11, "begsent \u2649\ufe0f": 10, "\u2649\ufe0f endsent": 10, "i have": 10, "have an": 10, "an attention": 10, "attention span": 10, "span of": 10, "of a": 10, "a goldfish": 10, "goldfish endsent": 10, "begsent ny/nj\u27a1\ufe0fsocal": 10, "ny/nj\u27a1\ufe0fsocal endsent": 10, "begsent musician.\ntoo": 8, "musician.\ntoo weird": 8, "weird to": 8, "to live,": 8, "live, too": 8, "too rare": 8, "rare to": 8, "to die.\nsc:jimmy-changa": 8, "die.\nsc:jimmy-changa endsent": 8, "begsent #elevon": 8, "#elevon @elevonfans": 8, "@elevonfans @_brytni": 8, "@_brytni ": 8, " @brytonejames": 8, "@brytonejames @mishaelmorgan1": 8, "@mishaelmorgan1 @empirefox": 8, "@empirefox @theellenshow": 8, "@theellenshow ": 8, " @nbcthevoice": 8, "@nbcthevoice @tamronhallshow": 8, "@tamronhallshow #biden2020": 8, "#biden2020 @joebiden": 8, "@joebiden @simplymishael": 8, "@simplymishael endsent": 8, "begsent silkk": 7, "silkk da": 7, " ": 7, "begsent la": 7, "la diablita..": 7, "diablita.. endsent": 7, "always be": 6, "national champion,": 6, "begsent catchin": 6, "catchin a": 6, "a vibe": 6, "vibe \ud83d\udda4": 6, "\ud83d\udda4 dre": 6, "dre from": 6, "from the": 6, "the west": 6, "west (909)": 6, "(909) txsu\ud83e\udd1f\ud83c\udffe\ud83e\udd75shawty": 6, "txsu\ud83e\udd1f\ud83c\udffe\ud83e\udd75shawty ft.": 6, "ft. i": 6, "am skram": 6, "skram out": 6, "out now": 6, "now #greatnessinspired": 6, "#greatnessinspired endsent": 6, "begsent \u201cwait.": 5, "\u201cwait. i": 5, "i hear": 5, "hear crying.": 5, "crying. oh,": 5, "oh, it\u2019s": 5, "it\u2019s just": 5, "just me.\u201d": 5, "me.\u201d endsent": 5, "am the": 5, "the prophet": 5, "prophet of": 5, "of god,": 5, "god, a": 5, "a soldier": 5, "soldier for": 5, "for moral": 5, "moral law.": 5, "law. learning": 5, "learning is": 5, "is good.": 5, "good. moral": 5, "moral law": 5, "law is": 5, "is leviticus.": 5, "leviticus. always": 5, "be good.": 5, "good. kindness": 5, "kindness and": 5, "and inocence": 5, "inocence is": 5, "is strength.": 5, "strength. endsent": 5, "begsent live.wavy": 4, "live.wavy now": 4, "now live\ud83d\udc95": 4, "live\ud83d\udc95 |": 4, "| ": 4, " wavyridge.yt@gmail.com": 4, "wavyridge.yt@gmail.com endsent": 4, "begsent those": 4, "those who": 4, "who abandon": 4, "abandon their": 4, "their friends": 4, "friends are": 4, "are worse": 4, "worse than": 4, "than scum": 4, "scum endsent": 4, "begsent ig:": 3, "ig: _mayrraa": 3, "_mayrraa |": 3, "| nick": 3, "nick \ud83d\udc9e": 3, "\ud83d\udc9e endsent": 3, "we are": 3, "the best": 3, "begsent 2012": 3, "2012 ama": 3, "ama u21": 3, "u21 national": 3, "champion, 2013": 3, "2013 ama": 3, "ama long": 3, "long track": 3, "track national": 3, "champion, 2014": 3, "2014 u21": 3, "u21 world": 3, "world finalist": 3, "finalist //": 3, "// mma": 3, "mma fighter": 3, "fighter (3-1)": 3, "(3-1) endsent": 3, "begsent \ud83d\ude4f\ud83c\udffer.i.p.": 3, "\ud83d\ude4f\ud83c\udffer.i.p. sean\ud83d\ude4f\ud83c\udffe": 3, "sean\ud83d\ude4f\ud83c\udffe |19|": 3, "|19| joshua": 3, "joshua 1:9": 3, "1:9 endsent": 3, "begsent entrepreneur\ud83d\udcb8,": 3, "entrepreneur\ud83d\udcb8, writer": 3, "writer \u270d\ufe0f": 3, "\u270d\ufe0f ,": 3, ", motivator": 3, "motivator \ud83d\ude4c.": 3, "\ud83d\ude4c. investor": 3, "investor \ud83d\udcb9": 3, "\ud83d\udcb9 microgreens": 3, "microgreens \ud83c\udf31": 3, "\ud83c\udf31 endsent": 3, "begsent contagion": 3, "contagion endsent": 3, "begsent overtime": 3, "overtime and": 3, "and overdue": 3, "overdue endsent": 3, "begsent #artist": 3, "#artist \ud83c\udfa8": 3, "\ud83c\udfa8 plant": 3, "plant enthusiast": 3, "enthusiast \ud83c\udf3f": 3, "\ud83c\udf3f &": 3, "& bird": 3, "bird lover/mother": 3, "lover/mother \ud83d\udc23": 3, "\ud83d\udc23 ": 3, " 23": 3, "23 |": 3, "| infp-tp": 3, "infp-tp |": 3, "| \ud83e\udd82\u264f": 3, "\ud83e\udd82\u264f #collageart": 3, "#collageart #acrylicpaint": 3, "#acrylicpaint #illustrator": 3, "#illustrator #designer": 3, "#designer insta": 3, "insta is": 3, "is @justjensart": 3, "@justjensart \ud83c\udff3\ufe0f\u200d\ud83c\udf08": 3, "\ud83c\udff3\ufe0f\u200d\ud83c\udf08 endsent": 3, "begsent #semperparatus...": 3, "#semperparatus... if": 3, "if you": 3, "you never": 3, "never make": 3, "make mistakes,": 3, "mistakes, you'll": 3, "you'll never": 3, "never learn...": 3, "learn... ig:": 3, "ig: nandoraptor": 3, "nandoraptor endsent": 3, "begsent phs": 2, "phs 2020": 2, "2020 \ud83d\udc3e\ud83d\udcda": 2, "\ud83d\udc3e\ud83d\udcda 18yrs": 2, "18yrs young": 2, "young \u270c\ud83c\udffb": 2, "\u270c\ud83c\udffb endsent": 2, "begsent ceo": 2, "ceo and": 2, "and founder": 2, "founder sealed": 2, "sealed with": 2, "with a": 2, "a kiss": 2, "kiss lip": 2, "lip care#teamfollowback": 2, "care#teamfollowback #teamlakers": 2, "#teamlakers all": 2, "all day": 2, "day in": 2, "in this": 2, "this ": 2, " #teamlibra": 2, "#teamlibra haha": 2, "haha cause": 2, "cause we": 2, "are the": 2, "best ask": 2, "ask about": 2, "about us...": 2, "us... endsent": 2, "begsent j\ud83d\udc98": 2, "j\ud83d\udc98 endsent": 2, "begsent player": 2, "player development": 2, "development |": 2, "| small": 2, "small group,": 2, "group, team": 2, "team training,": 2, "training, camps": 2, "camps &": 2, "& clinics": 2, "clinics |": 2, "| (951)": 2, "(951) 293-4255": 2, "293-4255 |": 2, "| kevinmitchellbasketball@gmail.com": 2, "kevinmitchellbasketball@gmail.com |": 2, "| \ud83d\udcc8": 2, "\ud83d\udcc8 growing": 2, "growing players": 2, "players \ud83e\uddf1": 2, "\ud83e\uddf1 x": 2, "x \ud83e\uddf1": 2, "\ud83e\uddf1 #moreworktodo": 2, "#moreworktodo endsent": 2, "begsent fth": 2, "fth foundation": 2, "foundation is": 2, "is a": 2, "a non-proft": 2, "non-proft charitable": 2, "charitable organization,": 2, "organization, dedicated": 2, "dedicated to": 2, "to improving": 2, "improving the": 2, "the quality": 2, "quality of": 2, "of life": 2, "life of": 2, "of under-": 2, "under- privileged": 2, "privileged children,": 2, "children, seniors": 2, "seniors &": 2, "& families.": 2, "families. est": 2, "est in": 2, "in 2014": 2, "2014 endsent": 2, "begsent fish": 2, "fish taco": 2, "taco express\n(mexican&seafood": 2, "express\n(mexican&seafood specialty.)\n951-349-0131\n1675": 2, "specialty.)\n951-349-0131\n1675 n.": 2, "n. perris": 2, "perris blvd,": 2, "blvd, ste": 2, "ste a-14,": 2, "a-14, perris,": 2, "perris, ca": 2, "ca 92571\n951-486-8355\n27126": 2, "92571\n951-486-8355\n27126 shadel": 2, "shadel rd,": 2, "rd, menifee,": 2, "menifee, ca": 2, "ca 92586": 2, "92586 endsent": 2, "begsent it\u2019s": 2, "begsent \ud83c\uddf2\ud83c\uddfd\ud83c\udde8\ud83c\uddf3": 2, "\ud83c\uddf2\ud83c\uddfd\ud83c\udde8\ud83c\uddf3 endsent": 2, "begsent yo": 2, "yo mama": 2, "mama bitch.": 2, "bitch. endsent": 2, "begsent \ud83c\uddf2\ud83c\uddfd\ud83c\uddfa\ud83c\uddf8": 2, "\ud83c\uddf2\ud83c\uddfd\ud83c\uddfa\ud83c\uddf8 endsent": 2, "begsent \ud835\udc17\ud835\udc08": 2, "\ud835\udc17\ud835\udc08 \u2800\u2800\u2800\ud835\udc17\ud835\udc17\ud835\udc08": 2, "\u2800\u2800\u2800\ud835\udc17\ud835\udc17\ud835\udc08 \u2800\u2800\u2800\ud835\udc17\ud835\udc08\ud835\udc17": 2, "\u2800\u2800\u2800\ud835\udc17\ud835\udc08\ud835\udc17 endsent": 2, "begsent \u2606.\uff61i": 2, "\u2606.\uff61i love": 2, "love wallets": 2, "wallets \ud801\udc2a\ud801\udc42": 2, "\ud801\udc2a\ud801\udc42 \u2661": 2, "\u2661 \ud801\udc2a\ud801\udc42": 2, "\ud801\udc2a\ud801\udc42 endsent": 2, "begsent its": 2, "its not": 2, "not about": 2, "about forcing": 2, "forcing happiness;": 2, "happiness; it\u2019s": 2, "it\u2019s about": 2, "about not": 2, "not letting": 2, "letting sadness": 2, "sadness win": 2, "win \u2728": 2, "\u2728 endsent": 2, "begsent \ud83c\udd42\ud83c\udd3b\ud83c\udd34\ud83c\udd34\ud83c\udd3f\ud83c\udd48": 1, "\ud83c\udd42\ud83c\udd3b\ud83c\udd34\ud83c\udd34\ud83c\udd3f\ud83c\udd48 \ud83c\udd38\ud83c\udd3d\ud83c\udd43\ud83c\udd41\ud83c\udd3e\ud83c\udd45\ud83c\udd34\ud83c\udd41\ud83c\udd43": 1, "\ud83c\udd38\ud83c\udd3d\ud83c\udd43\ud83c\udd41\ud83c\udd3e\ud83c\udd45\ud83c\udd34\ud83c\udd41\ud83c\udd43 ": 1, " \ud83e\udd0d\ud835\udca5.\ud83e\udd0d": 1, "\ud83e\udd0d\ud835\udca5.\ud83e\udd0d \ud835\udff7\ud835\udff6.\ud835\udff7\ud835\udffe.\ud835\udff7\ud835\udffd": 1, "\ud835\udff7\ud835\udff6.\ud835\udff7\ud835\udffe.\ud835\udff7\ud835\udffd endsent": 1, "begsent comunicando": 1, "comunicando vida": 1, "vida \ud83c\udf31\ud83c\udf99": 1, "\ud83c\udf31\ud83c\udf99 so\u00f1ando": 1, "so\u00f1ando en": 1, "en grande": 1, "grande \ud83d\udcad": 1, "\ud83d\udcad viajando": 1, "viajando \ud83e\uddf3": 1, "\ud83e\uddf3 \ud83c\udf0d": 1, "\ud83c\udf0d instagram": 1, "instagram y": 1, "y facebook:": 1, "facebook: @alexmendezoficial": 1, "@alexmendezoficial endsent": 1, "begsent cudfam": 1, "cudfam /": 1, "/ cactusjack": 1, "cactusjack endsent": 1, "begsent ig;": 1, "ig; mauriciogfitness": 1, "mauriciogfitness /": 1, "/ everyday": 1, "everyday we": 1, "are put": 1, "put to": 1, "the test,": 1, "test, so": 1, "so always": 1, "be the": 1, "best version": 1, "version of": 1, "of yourself.": 1, "yourself. endsent": 1, "begsent \u264f\ufe0f": 1, "\u264f\ufe0f endsent": 1, "begsent check": 1, "check me": 1, "me out": 1, "out \ud83e\udd18\ud83c\udffe\ud83c\udfc8": 1, "\ud83e\udd18\ud83c\udffe\ud83c\udfc8 ": 1, "it\u2019s summer": 1, "summer somewhere": 1, "somewhere so": 1, "so you": 1, "you shouldn\u2019t": 1, "shouldn\u2019t be": 1, "be so": 1, "so cold": 1, "cold endsent": 1, "it\u2019s a": 1, "a good": 1, "good time": 1, "time all": 1, "all the": 1, "the time": 1, "time endsent": 1, "begsent @terrorizeco": 1, "@terrorizeco endsent": 1, "begsent annelise": 1, "annelise \ud83d\udc95": 1, "\ud83d\udc95 \ud83d\ude91": 1, "\ud83d\ude91 endsent": 1, "begsent martin": 1, "martin gomez\u2764\ufe0f": 1, "gomez\u2764\ufe0f 11~21~19\ud83d\udc8d": 1, "11~21~19\ud83d\udc8d endsent": 1, "begsent calvary": 1, "calvary chapel": 1, "chapel perris": 1, "perris valley": 1, "valley twitter": 1, "twitter established": 1, "established to": 1, "to share": 1, "share the": 1, "the good": 1, "good news.": 1, "news. endsent": 1, "begsent idk": 1, "idk what": 1, "what to": 1, "to put!": 1, "put! endsent": 1, "begsent egomaniac": 1, "egomaniac with": 1, "with an": 1, "an inferiority": 1, "inferiority complex.": 1, "complex. j.e.m\ud83c\udf5c\ud83d\udc0d\u2019s\u2665\ufe0f": 1, "j.e.m\ud83c\udf5c\ud83d\udc0d\u2019s\u2665\ufe0f ": 1, "begsent follow": 1, "follow this": 1, "this account": 1, "account for": 1, "for geo-targeted": 1, "geo-targeted supply": 1, "supply chain": 1, "chain job": 1, "job tweets": 1, "tweets in": 1, "in orange": 1, "orange county,": 1, "county, ca.": 1, "ca. need": 1, "need help?": 1, "help? tweet": 1, "tweet us": 1, "us at": 1, "at @careerarc!": 1, "@careerarc! endsent": 1, "begsent representing": 1, "representing la's": 1, "la's sports": 1, "sports to": 1, "the fullest!!": 1, "fullest!! howard": 1, "howard stern": 1, "stern show": 1, "show fanatic": 1, "fanatic endsent": 1, "begsent \u02da\u2727\u208a\u204e19": 1, "\u02da\u2727\u208a\u204e19 |": 1, "| la": 1, "la \u204e\u207a\u02f3\u2727\u0f1a": 1, "\u204e\u207a\u02f3\u2727\u0f1a \ud83e\udd8b": 1, "\ud83e\udd8b endsent": 1, "begsent i\u2019m": 1, "i\u2019m good": 1, "good luv": 1, "luv endsent": 1, "begsent disfruta": 1, "disfruta la": 1, "la vida": 1, "vida porque": 1, "porque se": 1, "se aqaba": 1, "aqaba endsent": 1}